onnxeditor/__init__.py
onnxeditor/__main__.py
onnxeditor/onnx_editor.py
onnxeditor/gui/__init__.py
onnxeditor/gui/app.py
onnxeditor/gui/graph_editor.py
onnxeditor/gui/main_window.py
onnxeditor/gui/operator.py
onnxeditor/gui/graphics/__init__.py
onnxeditor/gui/graphics/edge.py
onnxeditor/gui/graphics/io_node.py
onnxeditor/gui/graphics/node.py
onnxeditor/gui/graphics/normal_node.py
onnxeditor/gui/graphics/scene.py
onnxeditor/gui/res/__init__.py
onnxeditor/gui/res/res.py
onnxeditor/gui/ui/__init__.py
onnxeditor/gui/ui/datainspector/__init__.py
onnxeditor/gui/ui/datainspector/datainspector.py
onnxeditor/gui/ui/datainspector/ui_datainspector.py
onnxeditor/gui/ui/findbar/__init__.py
onnxeditor/gui/ui/findbar/findbar.py
onnxeditor/gui/ui/findbar/ui_findbar.py
onnxeditor/gui/ui/iosummary/__init__.py
onnxeditor/gui/ui/iosummary/iosummary.py
onnxeditor/gui/ui/iosummary/ui_iosummary.py
onnxeditor/gui/ui/modeleditor/__init__.py
onnxeditor/gui/ui/modeleditor/modeleditor.py
onnxeditor/gui/ui/nodesummary/__init__.py
onnxeditor/gui/ui/nodesummary/nodesummary.py
onnxeditor/gui/ui/nodesummary/ui_nodesummary.py
onnxeditor/ir/__init__.py
onnxeditor/ir/base/__init__.py
onnxeditor/ir/base/graph.py
onnxeditor/ir/base/model.py
onnxeditor/ir/base/node.py
onnxeditor/ir/base/obj.py
onnxeditor/ir/base/variable.py
onnxeditor/ir/opt/__init__.py
onnxeditor/ir/opt/const_to_var.py
onnxeditor/ir/port/__init__.py
onnxeditor/ir/port/exp.py
onnxeditor/ir/port/imp.py
onnxeditor-0.1.1.dist-info/LICENSE
onnxeditor-0.1.1.dist-info/METADATA
onnxeditor-0.1.1.dist-info/WHEEL
onnxeditor-0.1.1.dist-info/entry_points.txt
onnxeditor-0.1.1.dist-info/top_level.txt
onnxeditor-0.1.1.dist-info/RECORD
