Metadata-Version: 2.1
Name: onnxeditor
Version: 0.1.1
Summary: A Qt base onnx editor
Home-page: https://github.com/OYCN/OnnxEditorV3
Author: oPluss
Author-email: opluss@qq.com
Requires-Python: >=3.6
License-File: LICENSE
Requires-Dist: numpy
Requires-Dist: pyside6
Requires-Dist: grandalf
Requires-Dist: onnx >=1.13.1
